{
    "total_pages": 10,
    "data": [
      {
        "id": "1",
        "company_name": "Stan株式会社",
        "sender_name": "手簀戸 Rikki",
        "sender_line_account_name": "テストタナカ",
        "sender_phone": "804-784-6235",
        "sender_email": "rikki.backer@loopsys.info",
        "sender_line_user_id": "5ee7fdafa0fd",
        "send_status": "0",
        "complete_flg": "0",
        "created_at": "2017-09-09 15:11:40",
        "send_at": "2015-06-29 15:44:75"
      },
      {
        "id": "2",
        "company_name": "Kirstie株式会社",
        "sender_name": "手簀戸 Heath",
        "sender_line_account_name": "テストタナカ",
        "sender_phone": "264-701-2466",
        "sender_email": "heath.wallis@dynaroc.net",
        "sender_line_user_id": "81ae127a1f21",
        "send_status": "1",
        "complete_flg": "0",
        "created_at": "2016-05-18 03:24:45",
        "send_at": "2014-02-14 06:44:37"
      },
      {
        "id": "3",
        "company_name": "Max株式会社",
        "sender_name": "手簀戸 Heath",
        "sender_line_account_name": "テストタナカ",
        "sender_phone": "807-591-0956",
        "sender_email": "heath.stine@multiserv.com",
        "sender_line_user_id": "0354f3543bcf",
        "send_status": "0",
        "complete_flg": "0",
        "created_at": "2016-04-23 13:13:21",
        "send_at": "2012-07-30 00:41:56"
      },
      {
        "id": "4",
        "company_name": "Roman株式会社",
        "sender_name": "手簀戸 Lloyd",
        "sender_line_account_name": "テストタナカ",
        "sender_phone": "984-669-8818",
        "sender_email": "lloyd.bourquin@cameratek.com",
        "sender_line_user_id": "0a7a2021a495",
        "send_status": "0",
        "complete_flg": "0",
        "created_at": "2014-02-17 00:32:04",
        "send_at": "2014-08-03 23:11:16"
      },
      {
        "id": "5",
        "company_name": "Cory株式会社",
        "sender_name": "手簀戸 Janett",
        "sender_line_account_name": "テストタナカ",
        "sender_phone": "137-421-0582",
        "sender_email": "janett.dampier@westgate.club",
        "sender_line_user_id": "5235207e5ff2",
        "send_status": "0",
        "complete_flg": "0",
        "created_at": "2010-06-21 23:27:76",
        "send_at": "2017-03-08 10:51:63"
      },
      {
        "id": "6",
        "company_name": "Eleanore株式会社",
        "sender_name": "手簀戸 Roselyn",
        "sender_line_account_name": "テストタナカ",
        "sender_phone": "752-383-5886",
        "sender_email": "roselyn.rhymer@solexis.org",
        "sender_line_user_id": "3f4ae9d9781d",
        "send_status": "0",
        "complete_flg": "0",
        "created_at": "2011-02-15 18:45:57",
        "send_at": "2015-08-21 07:38:63"
      },
      {
        "id": "7",
        "company_name": "Alejandro株式会社",
        "sender_name": "手簀戸 Isabelle",
        "sender_line_account_name": "テストタナカ",
        "sender_phone": "874-945-3197",
        "sender_email": "isabelle.shelly@coolinga.co",
        "sender_line_user_id": "99b384700be1",
        "send_status": "0",
        "complete_flg": "0",
        "created_at": "2016-01-05 07:32:79",
        "send_at": "2019-04-06 21:31:30"
      },
      {
        "id": "8",
        "company_name": "Alexa株式会社",
        "sender_name": "手簀戸 Cory",
        "sender_line_account_name": "テストタナカ",
        "sender_phone": "622-914-6421",
        "sender_email": "cory.flinn@infratouch.club",
        "sender_line_user_id": "e4d56e6559c1",
        "send_status": "1",
        "complete_flg": "0",
        "created_at": "2013-09-29 10:20:99",
        "send_at": "2011-12-07 12:08:76"
      },
      {
        "id": "9",
        "company_name": "Gavin株式会社",
        "sender_name": "手簀戸 Jenna",
        "sender_line_account_name": "テストタナカ",
        "sender_phone": "760-608-3350",
        "sender_email": "jenna.bradbury@skycenta.org",
        "sender_line_user_id": "16c207c28b46",
        "send_status": "0",
        "complete_flg": "0",
        "created_at": "2019-03-25 06:34:15",
        "send_at": "2014-02-02 19:35:09"
      },
      {
        "id": "10",
        "company_name": "Ian株式会社",
        "sender_name": "手簀戸 Raisa",
        "sender_line_account_name": "テストタナカ",
        "sender_phone": "276-213-4473",
        "sender_email": "raisa.charley@openserv.com",
        "sender_line_user_id": "41d435b2dff9",
        "send_status": "0",
        "complete_flg": "0",
        "created_at": "2010-06-01 19:30:89",
        "send_at": "2016-08-28 02:50:85"
      }
    ]
}

